README.rst
setup.py
addresslib/__init__.py
addresslib/address.py
addresslib/corrector.py
addresslib/dnsq.py
addresslib/expiringdict.py
addresslib/parser.py
addresslib/quote.py
addresslib/tokenizer.py
addresslib/utils.py
addresslib/validate.py
addresslib/drivers/__init__.py
addresslib/drivers/dns_lookup.py
addresslib/drivers/redis_driver.py
addresslib/plugins/__init__.py
addresslib/plugins/aol.py
addresslib/plugins/gmail.py
addresslib/plugins/google.py
addresslib/plugins/hotmail.py
addresslib/plugins/icloud.py
addresslib/plugins/yahoo.py
addresslib3.egg-info/PKG-INFO
addresslib3.egg-info/SOURCES.txt
addresslib3.egg-info/dependency_links.txt
addresslib3.egg-info/requires.txt
addresslib3.egg-info/top_level.txt
addresslib3.egg-info/zip-safe
tests/addresslib/__init__.py
tests/addresslib/address_test.py
tests/addresslib/corrector_test.py
tests/addresslib/external_dataset_test.py
tests/addresslib/metrics_test.py
tests/addresslib/parser_mailbox_test.py
tests/addresslib/parser_test.py
tests/addresslib/quote_test.py
tests/addresslib/validator_test.py
tests/addresslib/plugins/__init__.py
tests/addresslib/plugins/aol_test.py
tests/addresslib/plugins/gmail_test.py
tests/addresslib/plugins/google_test.py
tests/addresslib/plugins/hotmail_test.py
tests/addresslib/plugins/icloud_test.py
tests/addresslib/plugins/yahoo_test.py