Metadata-Version: 1.0
Name: addresslib3
Version: 0.4.27
Summary: Email Validation forked from Flanker, compatible with python3
Home-page: https://github.com/EncircleInc/addresslib
Author: Mailgun Inc., Encircle Inc.
Author-email: dev@encircleapp.com
License: Apache 2
Platform: UNKNOWN
